cmdtwiddler/__init__.py
cmdtwiddler/__main__.py
cmdtwiddler/cmdtwiddler.py
cmdtwiddler/RPCHelper.py
cmdtwiddler/supervisor_conf_file_parser.py
cmdtwiddler/test/__init__.py
cmdtwiddler/test/test_cmdtwiddler.py
cmdtwiddler-1.2.0.dist-info/DESCRIPTION.rst
cmdtwiddler-1.2.0.dist-info/entry_points.txt
cmdtwiddler-1.2.0.dist-info/METADATA
cmdtwiddler-1.2.0.dist-info/metadata.json
cmdtwiddler-1.2.0.dist-info/RECORD
cmdtwiddler-1.2.0.dist-info/top_level.txt
cmdtwiddler-1.2.0.dist-info/WHEEL
